jaraco/abode/__init__.py
jaraco/abode/__main__.py
jaraco/abode/_itertools.py
jaraco/abode/automation.py
jaraco/abode/cli.py
jaraco/abode/client.py
jaraco/abode/config.py
jaraco/abode/event_controller.py
jaraco/abode/exceptions.py
jaraco/abode/settings.py
jaraco/abode/socketio.py
jaraco/abode/state.py
jaraco/abode/devices/__init__.py
jaraco/abode/devices/alarm.py
jaraco/abode/devices/base.py
jaraco/abode/devices/binary_sensor.py
jaraco/abode/devices/camera.py
jaraco/abode/devices/cover.py
jaraco/abode/devices/light.py
jaraco/abode/devices/lock.py
jaraco/abode/devices/pkg.py
jaraco/abode/devices/sensor.py
jaraco/abode/devices/status.py
jaraco/abode/devices/switch.py
jaraco/abode/devices/valve.py
jaraco/abode/helpers/__init__.py
jaraco/abode/helpers/errors.py
jaraco/abode/helpers/events.csv
jaraco/abode/helpers/timeline.py
jaraco/abode/helpers/urls.py
jaraco.abode-6.2.1.dist-info/LICENSE
jaraco.abode-6.2.1.dist-info/METADATA
jaraco.abode-6.2.1.dist-info/WHEEL
jaraco.abode-6.2.1.dist-info/entry_points.txt
jaraco.abode-6.2.1.dist-info/top_level.txt
jaraco.abode-6.2.1.dist-info/RECORD
