Metadata-Version: 2.1
Name: jaraco.abode
Version: 6.2.1
Summary: A library interfacing to the Abode home security system
Author-email: Wil Schrader <wilrader@gmail.com>
Maintainer-email: "Jason R. Coombs" <jaraco@jaraco.com>
Project-URL: Source, https://github.com/jaraco/jaraco.abode
Classifier: Development Status :: 5 - Production/Stable
Classifier: Intended Audience :: Developers
Classifier: License :: OSI Approved :: MIT License
Classifier: Programming Language :: Python :: 3
Classifier: Programming Language :: Python :: 3 :: Only
Requires-Python: >=3.8
License-File: LICENSE
Requires-Dist: requests >=2.12.4
Requires-Dist: lomond >=0.3.3
Requires-Dist: colorlog >=3.0.1
Requires-Dist: keyring
Requires-Dist: requests-toolbelt
Requires-Dist: jaraco.collections
Requires-Dist: jaraco.context
Requires-Dist: jaraco.classes
Requires-Dist: jaraco.net >=9
Requires-Dist: more-itertools
Requires-Dist: importlib-resources >=5.10
Requires-Dist: bx-py-utils
Requires-Dist: platformdirs
Requires-Dist: jaraco.itertools
Requires-Dist: jaraco.functools >=3.6
Provides-Extra: check
Requires-Dist: pytest-checkdocs >=2.4 ; extra == 'check'
Requires-Dist: pytest-ruff >=0.2.1 ; (sys_platform != "cygwin") and extra == 'check'
Provides-Extra: cover
Requires-Dist: pytest-cov ; extra == 'cover'
Provides-Extra: doc
Requires-Dist: sphinx >=3.5 ; extra == 'doc'
Requires-Dist: jaraco.packaging >=9.3 ; extra == 'doc'
Requires-Dist: rst.linker >=1.9 ; extra == 'doc'
Requires-Dist: furo ; extra == 'doc'
Requires-Dist: sphinx-lint ; extra == 'doc'
Provides-Extra: enabler
Requires-Dist: pytest-enabler >=2.2 ; extra == 'enabler'
Provides-Extra: test
Requires-Dist: pytest !=8.1.*,>=6 ; extra == 'test'
Requires-Dist: requests-mock ; extra == 'test'
Requires-Dist: jaraco.collections >=4.1 ; extra == 'test'
Provides-Extra: type
Requires-Dist: pytest-mypy ; extra == 'type'
Requires-Dist: types-requests ; extra == 'type'
